mda/__init__.py
mda/mda.py
tests/__init__.py
tests/test_mda.py
MDA_learn-0.1.1.dist-info/LICENSE.txt
MDA_learn-0.1.1.dist-info/METADATA
MDA_learn-0.1.1.dist-info/WHEEL
MDA_learn-0.1.1.dist-info/top_level.txt
MDA_learn-0.1.1.dist-info/RECORD
