Metadata-Version: 2.1
Name: MDA-learn
Version: 0.1.1
Summary: Manifold Discovery and Analysis (MDA) algorithm for deep learning feature space analysis.
Home-page: https://github.com/your_github_repo
Author: Md Tauhidul Islam and Zixia Zhou et al.
Author-email: lei@stanford.edu
License: MIT
Classifier: Programming Language :: Python :: 3
Classifier: License :: OSI Approved :: MIT License
Classifier: Operating System :: OS Independent
Requires-Python: >=3.6
License-File: LICENSE.txt
Requires-Dist: numpy
Requires-Dist: scipy
Requires-Dist: scikit-learn
Requires-Dist: matplotlib
Requires-Dist: pandas
Requires-Dist: umap-learn
